pantsbuild.pants.contrib.awslambda_python-1.29.0-py3.6-nspkg.pth
pants/contrib/awslambda/__init__.py
pants/contrib/awslambda/python/__init__.py
pants/contrib/awslambda/python/register.py
pants/contrib/awslambda/python/target_types.py
pants/contrib/awslambda/python/targets/__init__.py
pants/contrib/awslambda/python/targets/python_awslambda.py
pants/contrib/awslambda/python/tasks/__init__.py
pants/contrib/awslambda/python/tasks/lambdex_prep.py
pants/contrib/awslambda/python/tasks/lambdex_run.py
pantsbuild.pants.contrib.awslambda_python-1.29.0.dist-info/METADATA
pantsbuild.pants.contrib.awslambda_python-1.29.0.dist-info/RECORD
pantsbuild.pants.contrib.awslambda_python-1.29.0.dist-info/WHEEL
pantsbuild.pants.contrib.awslambda_python-1.29.0.dist-info/entry_points.txt
pantsbuild.pants.contrib.awslambda_python-1.29.0.dist-info/namespace_packages.txt
pantsbuild.pants.contrib.awslambda_python-1.29.0.dist-info/top_level.txt
pantsbuild.pants.contrib.awslambda_python-1.29.0.dist-info/zip-safe
